cchdo/auth/__init__.py
cchdo/auth/__main__.py
cchdo/auth/py.typed
cchdo/auth/session.py
cchdo/auth/test/__init__.py
cchdo/auth/test/test_Auth.py
cchdo.auth-1.1.0.dist-info/LICENSE.md
cchdo.auth-1.1.0.dist-info/METADATA
cchdo.auth-1.1.0.dist-info/WHEEL
cchdo.auth-1.1.0.dist-info/top_level.txt
cchdo.auth-1.1.0.dist-info/RECORD
