Metadata-Version: 2.1
Name: cchdo.auth
Version: 1.1.0
Author-email: cchdo <cchdo@ucsd.edu>
License: BSD 3-clause
Project-URL: Homepage, https://cchdo.ucsd.edu/
Project-URL: Documentation, https://cchdo.github.io/auth
Project-URL: Repository, https://github.com/cchdo/auth.git
Classifier: Development Status :: 5 - Production/Stable
Classifier: Intended Audience :: Science/Research
Classifier: Operating System :: OS Independent
Classifier: License :: OSI Approved :: BSD License
Classifier: Programming Language :: Python
Classifier: Programming Language :: Python :: 3
Classifier: Programming Language :: Python :: 3.10
Classifier: Programming Language :: Python :: 3.11
Classifier: Programming Language :: Python :: 3.12
Classifier: Topic :: Scientific/Engineering
Requires-Python: >=3.10
License-File: LICENSE.md
Requires-Dist: requests >=2.23.0
Requires-Dist: click >=7.0.0
Requires-Dist: appdirs >=1.4.0
Provides-Extra: complete
Requires-Dist: cchdo.auth[dev,docs] ; extra == 'complete'
Provides-Extra: dev
Requires-Dist: cchdo.auth[selftest] ; extra == 'dev'
Requires-Dist: coverage ; extra == 'dev'
Requires-Dist: pytest-cov ; extra == 'dev'
Requires-Dist: pre-commit ; extra == 'dev'
Requires-Dist: requests-mock ; extra == 'dev'
Requires-Dist: mypy ; extra == 'dev'
Requires-Dist: types-requests ; extra == 'dev'
Requires-Dist: ruff ; extra == 'dev'
Provides-Extra: docs
Requires-Dist: Sphinx ; extra == 'docs'
Requires-Dist: furo ; extra == 'docs'
Provides-Extra: selftest
Requires-Dist: pytest ; extra == 'selftest'
Requires-Dist: pyfakefs ; extra == 'selftest'
